README.rst
setup.cfg
setup.py
lacore_technologies/__init__.py
lacore_technologies.egg-info/PKG-INFO
lacore_technologies.egg-info/SOURCES.txt
lacore_technologies.egg-info/dependency_links.txt
lacore_technologies.egg-info/not-zip-safe
lacore_technologies.egg-info/requires.txt
lacore_technologies.egg-info/top_level.txt