Metadata-Version: 1.1
Name: lacore-technologies
Version: 1.0.16
Summary: Lacore API Python client
Home-page: https://www.lacoretechnologies.com/payment-services/
Author: Lacore Technologies
Author-email: support@lacoretechnologies.com
License: MIT License
Platform: UNKNOWN
Classifier: Intended Audience :: Developers
Classifier: License :: OSI Approved :: MIT License
Classifier: Programming Language :: Python
Classifier: Topic :: Software Development :: Libraries :: Python Modules
